hspf_utils/__init__.py
hspf_utils/hspf_utils.py
hspf_utils-6.0.10.dist-info/LICENSE.txt
hspf_utils-6.0.10.dist-info/METADATA
hspf_utils-6.0.10.dist-info/WHEEL
hspf_utils-6.0.10.dist-info/entry_points.txt
hspf_utils-6.0.10.dist-info/top_level.txt
hspf_utils-6.0.10.dist-info/RECORD
