Metadata-Version: 2.1
Name: hspf_utils
Version: 6.0.10
Summary: Command line script and Python library to develop water balance from HSPF models
Author-email: Tim Cera <tim@cerazone.net>
License: BSD-3-Clause
Project-URL: documentation, https://timcera.bitbucket.io/hspf_utils/docs/index.html#hspf_utils-documentation
Project-URL: github, https://github.com/timcera/hspf_utils
Project-URL: bitbucket, https://bitbucket.org/timcera/hspf_utils/src/main/
Keywords: python,cli-app,hspf,watershed,hydrology,hydrologic,simulation
Classifier: Development Status :: 5 - Production/Stable
Classifier: Intended Audience :: Science/Research
Classifier: Intended Audience :: End Users/Desktop
Classifier: Intended Audience :: Developers
Classifier: Environment :: Console
Classifier: License :: OSI Approved :: BSD License
Classifier: Natural Language :: English
Classifier: Operating System :: OS Independent
Classifier: Programming Language :: Python :: 3 :: Only
Classifier: Programming Language :: Python :: 3.8
Classifier: Programming Language :: Python :: 3.9
Classifier: Programming Language :: Python :: 3.10
Classifier: Programming Language :: Python :: 3.11
Classifier: Topic :: Scientific/Engineering :: Information Analysis
Classifier: Topic :: Scientific/Engineering
Classifier: Topic :: Software Development :: Libraries :: Python Modules
Requires-Python: >=3.8
License-File: LICENSE.txt
Requires-Dist: toolbox-utils<6.0.0,>=5.0.0
Requires-Dist: cltoolbox>1.1.0
Requires-Dist: hspfbintoolbox<10.0.0,>=9.0.0
Provides-Extra: dev
Requires-Dist: bandit; extra == "dev"
Requires-Dist: black; extra == "dev"
Requires-Dist: blacken-docs; extra == "dev"
Requires-Dist: black-nbconvert; extra == "dev"
Requires-Dist: cleanpy; extra == "dev"
Requires-Dist: commitizen; extra == "dev"
Requires-Dist: coverage[toml]; extra == "dev"
Requires-Dist: isort; extra == "dev"
Requires-Dist: mypy; extra == "dev"
Requires-Dist: pre-commit; extra == "dev"
Requires-Dist: pyflakes; extra == "dev"
Requires-Dist: pylama; extra == "dev"
Requires-Dist: pyle; extra == "dev"
Requires-Dist: pylint; extra == "dev"
Requires-Dist: pyre; extra == "dev"
Requires-Dist: pyroma; extra == "dev"
Requires-Dist: pytest; extra == "dev"
Requires-Dist: pytest-cov; extra == "dev"
Requires-Dist: pytest-mpl; extra == "dev"
Requires-Dist: pyupgrade; extra == "dev"
Requires-Dist: twine; extra == "dev"
Requires-Dist: unimport; extra == "dev"
Requires-Dist: velin; extra == "dev"
Requires-Dist: vulture; extra == "dev"
